dtumathtools/__init__.py
dtumathtools/dtuplot/__init__.py
dtumathtools/dtuplot/boundaryplot.py
dtumathtools/dtuplot/quiverplot.py
dtumathtools/dtuplot/quiverplot_helpers.py
dtumathtools/dtuplot/scatterplot.py
dtumathtools/dtutools/__init__.py
dtumathtools/dtutools/helpers.py
dtumathtools-2025.2.0.dist-info/licenses/LICENSE
dtumathtools-2025.2.0.dist-info/METADATA
dtumathtools-2025.2.0.dist-info/WHEEL
dtumathtools-2025.2.0.dist-info/top_level.txt
dtumathtools-2025.2.0.dist-info/RECORD
