Metadata-Version: 2.4
Name: dtumathtools
Version: 2025.2.0
Summary: A plotting package for the Mathematics 1a/1b courses at the Technical University of Denmark
Author-email: Christian Mikkelstrup <s194345@student.dtu.dk>, Hans Henrik Hermansen <s194042@student.dtu.dk>
Maintainer-email: Christian Mikkelstrup <s194345@student.dtu.dk>
License: BSD-3-Clause
Project-URL: Url, https://github.com/dtudk/dtumathtools
Project-URL: Homepage, https://github.com/dtudk/dtumathtools
Project-URL: Releases, https://github.com/dtudk/dtumathtools/releases
Project-URL: Documentation, https://github.com/dtudk/dtumathtools
Project-URL: Repository, https://github.com/dtudk/dtumathtools.git
Project-URL: Source, https://github.com/dtudk/dtumathtools
Project-URL: Tracker, https://github.com/dtudk/dtumathtools/issues
Project-URL: Discussions, https://github.com/dtudk/dtumathtools/discussions
Project-URL: Chat, https://discord.gg/h8EVaV9ShP
Classifier: Programming Language :: Python :: 3 :: Only
Classifier: Programming Language :: Python :: 3.9
Classifier: Programming Language :: Python :: 3.10
Classifier: Programming Language :: Python :: 3.11
Classifier: Programming Language :: Python :: 3.12
Classifier: License :: OSI Approved :: BSD License
Classifier: Operating System :: OS Independent
Classifier: Development Status :: 5 - Production/Stable
Classifier: Intended Audience :: Education
Classifier: Topic :: Education
Classifier: Topic :: Scientific/Engineering :: Mathematics
Requires-Python: <3.13,>=3.9
License-File: LICENSE
Requires-Dist: sympy-plot-backends<3.3,>=3.1.1; python_version <= "3.9"
Requires-Dist: sympy-plot-backends<4.0,>=3.4; python_version >= "3.10"
Requires-Dist: sympy~=1.12
Requires-Dist: matplotlib<3.10,>=3.8
Requires-Dist: jupyter>=1.0.0
Requires-Dist: numpy<2,>=1.24
Provides-Extra: ipympl
Requires-Dist: ipympl>=0.7.0; extra == "ipympl"
Provides-Extra: plotly
Requires-Dist: plotly>=4.14.3; extra == "plotly"
Provides-Extra: bokeh
Requires-Dist: panel>=1.0.0; extra == "bokeh"
Requires-Dist: ipywidgets_bokeh; extra == "bokeh"
Requires-Dist: colorcet; extra == "bokeh"
Provides-Extra: k3d
Requires-Dist: vtk; extra == "k3d"
Requires-Dist: k3d>=2.9.7; extra == "k3d"
Provides-Extra: qt
Requires-Dist: PyQt5~=5.15.9; extra == "qt"
Provides-Extra: test
Requires-Dist: pytest; extra == "test"
Provides-Extra: dev
Requires-Dist: flake8; extra == "dev"
Requires-Dist: black; extra == "dev"
Dynamic: license-file
